pytherpreter/__init__.py
pytherpreter/async_python_interpreter.py
pytherpreter/python_interpreter.py
pytherpreter/utils.py
pytherpreter-0.2.3.dist-info/LICENSE
pytherpreter-0.2.3.dist-info/METADATA
pytherpreter-0.2.3.dist-info/WHEEL
pytherpreter-0.2.3.dist-info/top_level.txt
pytherpreter-0.2.3.dist-info/zip-safe
pytherpreter-0.2.3.dist-info/RECORD
