Metadata-Version: 2.2
Name: pytherpreter
Version: 0.2.3
Summary: A Python interpreter with built-in safeguards for executing untrusted code, like LLM-generated scripts.
Author: Are Meisfjord, The HuggingFace Inc. team
License: Apache 2.0
Project-URL: Homepage, https://github.com/aremeis/pytherpreter
Project-URL: Bug Tracker, https://github.com/aremeis/pytherpreter/issues
Classifier: Development Status :: 3 - Alpha
Classifier: Intended Audience :: Developers
Classifier: License :: OSI Approved :: Apache Software License
Classifier: Programming Language :: Python :: 3
Classifier: Programming Language :: Python :: 3.10
Classifier: Programming Language :: Python :: 3.11
Classifier: Programming Language :: Python :: 3.12
Classifier: Programming Language :: Python :: 3.13
Classifier: Topic :: Software Development :: Libraries :: Python Modules
Requires-Python: >=3.10
License-File: LICENSE
